[
    {
        "title": "The Hobbit",
        "author": "J.R.R. Tolkien",
        "pages": 295,
        "status": "Read"
    },
    {
        "title": "1984",
        "author": "George Orwell",
        "pages": 328,
        "status": "Read"
    },
    {
        "title": "To Kill a Mockingbird",
        "author": "Harper Lee",
        "pages": 281,
        "status": "Read"
    },
    {
        "title": "Pride and Prejudice",
        "author": "Jane Austen",
        "pages": 279,
        "status": "Not Read"
    },
    {
        "title": "Moby Dick",
        "author": "Herman Melville",
        "pages": 585,
        "status": "Not Read"
    },
    {
        "title": "The Great Gatsby",
        "author": "F. Scott Fitzgerald",
        "pages": 180,
        "status": "Read"
    },
    {
        "title": "Brave New World",
        "author": "Aldous Huxley",
        "pages": 268,
        "status": "Not Read"
    },
    {
        "title": "The Catcher in the Rye",
        "author": "J.D. Salinger",
        "pages": 214,
        "status": "Read"
    },
    {
        "title": "Fahrenheit 451",
        "author": "Ray Bradbury",
        "pages": 158,
        "status": "Not Read"
    },
    {
        "title": "The Alchemist",
        "author": "Paulo Coelho",
        "pages": 208,
        "status": "Reading"
    }
]
